Workbook

Sheet Base de Dados
A1: ID | B1: Data | C1: Produto | D1: Categoria | E1: Vendedor | F1: Região | G1: Quantidade | H1: Preço Unitário | I1: Valor Total | J1: Cliente | K1: Forma Pagamento
A2: 1 | B2: 29/01/2025 | C2: Suporte Monitor | D2: Móveis | E2: Fernanda Souza | F2: Sul | G2: 11 | H2: 122.24602 | I2: 1344.7062 | J2: Empresa A | K2: Transferência
A3: 2 | B3: 29/01/2025 | C3: Luminária | D3: Móveis | E3: Ricardo Lima | F3: Oeste | G3: 16 | H3: 90.996728 | I3: 1455.9477 | J3: Cliente Individual | K3: Cartão Crédito
A4: 3 | B4: 28/01/2025 | C4: Tablet | D4: Eletrônicos | E4: Pedro Alves | F4: Sul | G4: 12 | H4: 1267.8299 | I4: 15213.959 | J4: Cliente Individual | K4: PIX
A5: 4 | B5: 03/01/2025 | C5: Luminária | D5: Móveis | E5: Maria Oliveira | F5: Norte | G5: 20 | H5: 85.488994 | I5: 1709.7799 | J5: Empresa A | K5: Transferência
A6: 5 | B6: 17/01/2025 | C6: Tablet | D6: Eletrônicos | E6: Pedro Alves | F6: Norte | G6: 16 | H6: 1313.3382 | I6: 21013.412 | J6: E-commerce Alpha | K6: Cartão Débito
A7: 6 | B7: 31/01/2025 | C7: Teclado | D7: Informática | E7: Maria Oliveira | F7: Centro | G7: 12 | H7: 113.40923 | I7: 1360.9108 | J7: Corporação Beta | K7: Cartão Débito
A8: 7 | B8: 07/01/2025 | C8: Monitor | D8: Informática | E8: Maria Oliveira | F8: Norte | G8: 7 | H8: 845.8071 | I8: 5920.6497 | J8: Empresa D | K8: Cartão Débito
A9: 8 | B9: 31/01/2025 | C9: Webcam | D9: Informática | E9: Ana Silva | F9: Norte | G9: 15 | H9: 254.50967 | I9: 3817.645 | J9: Varejo Z | K9: Boleto
A10: 9 | B10: 07/02/2025 | C10: Notebook | D10: Informática | E10: Ana Silva | F10: Sul | G10: 19 | H10: 3574.9747 | I10: 67924.519 | J10: Distribuidor Y | K10: Cartão Débito
A11: 10 | B11: 03/01/2025 | C11: Mouse | D11: Informática | E11: Fernanda Souza | F11: Sul | G11: 15 | H11: 49.184897 | I11: 737.77345 | J11: Empresa A | K11: PIX
A12: 11 | B12: 03/01/2025 | C12: Webcam | D12: Informática | E12: João Pereira | F12: Oeste | G12: 10 | H12: 270.10093 | I12: 2701.0093 | J12: Varejo Z | K12: Transferência
A13: 12 | B13: 31/01/2025 | C13: Mesa | D13: Móveis | E13: Pedro Alves | F13: Sul | G13: 13 | H13: 489.61545 | I13: 6365.0008 | J13: Loja X | K13: Boleto
... A501: 500 | B501: 05/01/2025 | C501: Carregador | D501: Eletrônicos | E501: Fernanda Souza | F501: Sul | G501: 6 | H501: 64.149519 | I501: 384.89711 | J501: Empresa B | K501: Cartão Débito

Sheet Análise
B2: ANÁLISE DE VENDAS
B4: Vendas por Categoria | E4: Top 5 Produtos Mais Vendidos
B5: Categoria | C5: Total Vendas | E5: Produto | F5: Quantidade
B6: Informática | C6: =SUMIF('Base de Dados'!D:D,B6,'Base de Dados'!I:I) -> 1580307.2 | E6: Notebook | F6: =SUMIF('Base de Dados'!C:C,E6,'Base de Dados'!G:G) -> 308
B7: Eletrônicos | C7: =SUMIF('Base de Dados'!D:D,B7,'Base de Dados'!I:I) -> 1388742.7 | E7: Smartphone | F7: =SUMIF('Base de Dados'!C:C,E7,'Base de Dados'!G:G) -> 254
B8: Móveis | C8: =SUMIF('Base de Dados'!D:D,B8,'Base de Dados'!I:I) -> 831746.52 | E8: Tablet | F8: =SUMIF('Base de Dados'!C:C,E8,'Base de Dados'!G:G) -> 388
E9: Monitor | F9: =SUMIF('Base de Dados'!C:C,E9,'Base de Dados'!G:G) -> 389
B10: Vendas por Região | E10: Cadeira Gamer | F10: =SUMIF('Base de Dados'!C:C,E10,'Base de Dados'!G:G) -> 427
B11: Região | C11: Total Vendas
B12: Norte | C12: =SUMIF('Base de Dados'!F:F,B12,'Base de Dados'!I:I) -> 717631.18
B13: Sul | C13: =SUMIF('Base de Dados'!F:F,B13,'Base de Dados'!I:I) -> 784071.42
B14: Leste | C14: =SUMIF('Base de Dados'!F:F,B14,'Base de Dados'!I:I) -> 870405.2
B15: Oeste | C15: =SUMIF('Base de Dados'!F:F,B15,'Base de Dados'!I:I) -> 604857.67
B16: Centro | C16: =SUMIF('Base de Dados'!F:F,B16,'Base de Dados'!I:I) -> 823830.96
B18: Top 5 Vendedores
B19: Vendedor | C19: Total Vendas
B20: Ana Silva | C20: =SUMIF('Base de Dados'!E:E,B20,'Base de Dados'!I:I) -> 486565.55
B21: Carlos Santos | C21: =SUMIF('Base de Dados'!E:E,B21,'Base de Dados'!I:I) -> 689589.44
B22: Maria Oliveira | C22: =SUMIF('Base de Dados'!E:E,B22,'Base de Dados'!I:I) -> 346359.72
B23: João Pereira | C23: =SUMIF('Base de Dados'!E:E,B23,'Base de Dados'!I:I) -> 397927.87
B24: Paula Costa | C24: =SUMIF('Base de Dados'!E:E,B24,'Base de Dados'!I:I) -> 509755.94

Sheet Dashboard
B2: DASHBOARD DE VENDAS
B4: RECEITA TOTAL | D4: TOTAL DE VENDAS | F4: TICKET MÉDIO
B5: =SUM('Base de Dados'!I:I) -> 3800796.4 | D5: =COUNTA('Base de Dados'!A:A)-1 -> 500 | F5: =B5/D5 -> 7601.5928
